{
  "expire_suffix_list": [".nut.m"],
  "file_info": {
    "action": [0,16995],
    "application": [16995,11441],
    "baselayer": [28436,1747],
    "basepicture": [30183,4792],
    "basiclayer": [34975,2133],
    "basicpicture": [37108,23667],
    "basicrender": [60775,3998],
    "basictext": [64773,1239],
    "confirmdialog": [66012,1649],
    "debug": [67661,6095],
    "dmmauth": [73756,1685],
    "doublepicture": [75441,8379],
    "envenv": [83820,7874],
    "envplayer": [91694,74953],
    "envsystem": [166647,8514],
    "exception": [175161,1097],
    "fontinfo": [176258,994],
    "gestureinfo": [177252,3714],
    "include": [180966,314],
    "init": [181280,6753],
    "main": [188033,998],
    "minigame": [189031,17884],
    "motionpanel": [206915,57299],
    "override": [264214,27933],
    "savesystem": [292147,37816],
    "selectdialog": [329963,1421],
    "sound": [331384,7755],
    "spec": [339139,608],
    "spec_ps3": [339747,1068],
    "spec_ps4": [340815,394],
    "spec_psp": [341209,466],
    "spec_vita": [341675,459],
    "spec_win": [342134,607],
    "spec_x360": [342741,671],
    "startup": [343412,705],
    "system": [344117,17611],
    "text": [361728,915],
    "title": [362643,142],
    "tus": [362785,2373],
    "util": [365158,6647],
    "world": [371805,17802]
  },
  "id": "archive",
  "version": 1.0
}